README.rst
setup.cfg
setup.py
graphene_pynamodb/__init__.py
graphene_pynamodb/converter.py
graphene_pynamodb/fields.py
graphene_pynamodb/registry.py
graphene_pynamodb/relationships.py
graphene_pynamodb/types.py
graphene_pynamodb/utils.py
graphene_pynamodb.egg-info/PKG-INFO
graphene_pynamodb.egg-info/SOURCES.txt
graphene_pynamodb.egg-info/dependency_links.txt
graphene_pynamodb.egg-info/requires.txt
graphene_pynamodb.egg-info/top_level.txt
graphene_pynamodb/tests/__init__.py
graphene_pynamodb/tests/models.py
graphene_pynamodb/tests/test_converter.py
graphene_pynamodb/tests/test_query.py
graphene_pynamodb/tests/test_relationships.py
graphene_pynamodb/tests/test_schema.py
graphene_pynamodb/tests/test_types.py
graphene_pynamodb/tests/test_utils.py