Metadata-Version: 1.1
Name: graphene-pynamodb
Version: 1.0.0
Summary: Graphene PynamoDB integration
Home-page: https://github.com/yfilali/graphql-pynamodb
Author: Yacine Filali
Author-email: yfilali@gmail.com
License: MIT
Keywords: api graphql protocol rest relay graphene pynamodb dynamodb
Platform: UNKNOWN
Classifier: Development Status :: 4 - Beta
Classifier: Intended Audience :: Developers
Classifier: Topic :: Software Development :: Libraries
Classifier: Programming Language :: Python :: 2
Classifier: Programming Language :: Python :: 2.7
Classifier: Programming Language :: Python :: 3
Classifier: Programming Language :: Python :: 3.3
Classifier: Programming Language :: Python :: 3.4
Classifier: Programming Language :: Python :: 3.5
Classifier: Programming Language :: Python :: Implementation :: PyPy
